recmetrics/__init__.py
recmetrics/metrics.py
recmetrics/plots.py
recmetrics-0.1.0.dist-info/LICENSE
recmetrics-0.1.0.dist-info/WHEEL
recmetrics-0.1.0.dist-info/METADATA
recmetrics-0.1.0.dist-info/RECORD
